pydeid/__init__.py
pydeid-0.0.1.dist-info/LICENSE
pydeid-0.0.1.dist-info/METADATA
pydeid-0.0.1.dist-info/WHEEL
pydeid-0.0.1.dist-info/top_level.txt
pydeid-0.0.1.dist-info/RECORD
